webcam_security/__init__.py
webcam_security/cli.py
webcam_security/config.py
webcam_security/core.py
webcam_security/telegram_bot.py
webcam_security/updater.py
webcam_security-0.3.25.dist-info/licenses/LICENSE
webcam_security-0.3.25.dist-info/METADATA
webcam_security-0.3.25.dist-info/WHEEL
webcam_security-0.3.25.dist-info/entry_points.txt
webcam_security-0.3.25.dist-info/top_level.txt
webcam_security-0.3.25.dist-info/RECORD
