Metadata-Version: 2.4
Name: webcam-security
Version: 0.3.25
Summary: A webcam security monitoring system with Telegram notifications
Home-page: https://github.com/JavierOramas/webcam-security
Author: Javier Oramas
Author-email: Javier Oramas <javiale2000@gmail.com>
License: MIT
Project-URL: Homepage, https://github.com/JavierOramas/webcam
Project-URL: Repository, https://github.com/JavierOramas/webcam
Project-URL: Issues, https://github.com/JavierOramas/webcam/issues
Classifier: Development Status :: 4 - Beta
Classifier: Intended Audience :: End Users/Desktop
Classifier: License :: OSI Approved :: MIT License
Classifier: Programming Language :: Python :: 3
Classifier: Programming Language :: Python :: 3.8
Classifier: Programming Language :: Python :: 3.9
Classifier: Programming Language :: Python :: 3.10
Classifier: Programming Language :: Python :: 3.11
Classifier: Programming Language :: Python :: 3.13
Requires-Python: >=3.8
License-File: LICENSE
Requires-Dist: opencv-python>=4.5.0
Requires-Dist: imutils>=0.5.4
Requires-Dist: requests>=2.25.0
Requires-Dist: typer>=0.9.0
Requires-Dist: rich>=13.0.0
Requires-Dist: sounddevice>=0.4.0
Requires-Dist: soundfile>=0.12.0
Requires-Dist: ffmpeg-python>=0.2.0
Requires-Dist: pydantic>=2.0.0
Requires-Dist: setuptools>=61.0
Provides-Extra: dev
Requires-Dist: pytest>=7.0.0; extra == "dev"
Requires-Dist: pytest-cov>=4.0.0; extra == "dev"
Requires-Dist: black>=22.0.0; extra == "dev"
Requires-Dist: ruff>=0.1.0; extra == "dev"
Requires-Dist: mypy>=1.0.0; extra == "dev"
Requires-Dist: pre-commit>=3.0.0; extra == "dev"
Provides-Extra: test
Requires-Dist: pytest>=7.0.0; extra == "test"
Requires-Dist: pytest-cov>=4.0.0; extra == "test"
Requires-Dist: pytest-mock>=3.10.0; extra == "test"
Dynamic: author
Dynamic: home-page
Dynamic: license-file
Dynamic: requires-python
